aws_lambda_manager-1.0.0.dist-info/licenses/LICENSE
lambda_manager/__init__.py
lambda_manager/lambda_manager.py
aws_lambda_manager-1.0.0.dist-info/METADATA
aws_lambda_manager-1.0.0.dist-info/WHEEL
aws_lambda_manager-1.0.0.dist-info/top_level.txt
aws_lambda_manager-1.0.0.dist-info/RECORD
