Metadata-Version: 2.4
Name: aws-lambda-manager
Version: 1.0.0
Summary: Herramienta simple y directa para administrar AWS Lambda y EventBridge desde Python
Home-page: https://pypi.org/project/lambda-manager/
Author: Edwin Caicedo Venté
Author-email: Edwin Caicedo Venté <ecaicedo@rapicredit.com>
Maintainer-email: Edwin Caicedo Venté <ecaicedo@rapicredit.com>
License: MIT
Project-URL: Homepage, https://pypi.org/project/lambda-manager/
Project-URL: Documentation, https://pypi.org/project/lambda-manager/
Keywords: aws,lambda,eventbridge,boto3,automation,serverless,cloud,management
Classifier: Development Status :: 5 - Production/Stable
Classifier: Intended Audience :: Developers
Classifier: Intended Audience :: System Administrators
Classifier: License :: OSI Approved :: MIT License
Classifier: Operating System :: OS Independent
Classifier: Programming Language :: Python :: 3
Classifier: Programming Language :: Python :: 3.7
Classifier: Programming Language :: Python :: 3.8
Classifier: Programming Language :: Python :: 3.9
Classifier: Programming Language :: Python :: 3.10
Classifier: Programming Language :: Python :: 3.11
Classifier: Programming Language :: Python :: 3.12
Classifier: Topic :: Software Development :: Libraries :: Python Modules
Classifier: Topic :: System :: Systems Administration
Classifier: Topic :: Internet :: WWW/HTTP :: Dynamic Content
Classifier: Topic :: Software Development :: Testing
Classifier: Environment :: Console
Classifier: Natural Language :: Spanish
Classifier: Natural Language :: English
Requires-Python: >=3.7
License-File: LICENSE
Requires-Dist: boto3>=1.26.0
Requires-Dist: botocore>=1.29.0
Provides-Extra: dev
Requires-Dist: pytest>=6.0; extra == "dev"
Requires-Dist: pytest-cov>=2.0; extra == "dev"
Requires-Dist: black>=21.0; extra == "dev"
Requires-Dist: flake8>=3.8; extra == "dev"
Requires-Dist: mypy>=0.800; extra == "dev"
Dynamic: author
Dynamic: home-page
Dynamic: license-file
Dynamic: requires-python
